YAEP/__init__.py
YAEP/earley.py
YAEP/main.py
YAEP/utils.py
PyParseEarley-1.0.1.dist-info/LICENSE
PyParseEarley-1.0.1.dist-info/METADATA
PyParseEarley-1.0.1.dist-info/WHEEL
PyParseEarley-1.0.1.dist-info/top_level.txt
PyParseEarley-1.0.1.dist-info/RECORD
