Metadata-Version: 2.1
Name: PyParseEarley
Version: 1.0.1
Summary: Yet Another Earley Parser: Efficient parsing algorithm for context-free grammars.
Home-page: https://github.com/t3bol90/YAEP
Author: Toan Doan
Author-email: toandd.i81@gmail.com
License: MIT
Platform: linux
Platform: windows
Platform: macos
Requires-Python: >=3.5
License-File: LICENSE
Requires-Dist: pydot
Requires-Dist: cairosvg
